var windmolenparken = {
"type": "FeatureCollection",
"name": "windmolenparken3",
"crs": { "type": "name", "properties": { "name": "urn:ogc:def:crs:OGC:1.3:CRS84" } },
"features": [
{ "type": "Feature", "properties": { "Windpark": "Borssele I en II", "Latitude": 51.64, "Longitude": 3.069972, "Aantal_windmolens": 94, "Vermogen_per_windmolen_MW": 8.0, "Vermogen_windpark_MW": 752.0, "in_gebruik_sinds": 2020, "oppervlakte": 344, "bedrijf": "Ørsted", "foto": "https://img.offshore-mag.com/files/base/ebm/os/image/2020/09/Borssele_1_2.5f4fdfeeeab39.png?auto=format&w=720", ";;": ";;" }, "geometry": { "type": "Point", "coordinates": [ 3.069972, 51.64 ] } },
{ "type": "Feature", "properties": { "Windpark": "Borssele III en IV", "Latitude": 51.74, "Longitude": 2.879972, "Aantal_windmolens": 77, "Vermogen_per_windmolen_MW": 9.5, "Vermogen_windpark_MW": 731.5, "in_gebruik_sinds": 2020, "oppervlakte": 344, "bedrijf": "Blauwwind ", "foto": "https://www.nsenergybusiness.com/wp-content/uploads/sites/3/2020/08/Blauwwind-740x520.jpg", ";;": ";;" }, "geometry": { "type": "Point", "coordinates": [ 2.879972, 51.74 ] } },
{ "type": "Feature", "properties": { "Windpark": "Gemini Windpark", "Latitude": 54.036, "Longitude": 5.963, "Aantal_windmolens": 150, "Vermogen_per_windmolen_MW": 4.0, "Vermogen_windpark_MW": 600.0, "in_gebruik_sinds": 2016, "oppervlakte": 68, "bedrijf": "Northland Power, Siemens, HVC, Alte Leipziger/Hallesche", "foto": "https://www.deingenieur.nl/uploads/cache/article_detail_image/uploads/media/5910561ec4cf6/Gemini%20windpark.jpg", ";;": ";;" }, "geometry": { "type": "Point", "coordinates": [ 5.963, 54.036 ] } },
{ "type": "Feature", "properties": { "Windpark": "Luchterduinen", "Latitude": 52.403139, "Longitude": 4.165139, "Aantal_windmolens": 43, "Vermogen_per_windmolen_MW": 3.0, "Vermogen_windpark_MW": 129.0, "in_gebruik_sinds": 2015, "oppervlakte": 25, "bedrijf": "Eneco, Mitsubishi Corporatio (MC) ", "foto": "https://cdn1.nrgedge.net/company/nrg3cb0291d9b3f8342fb85a702481c56fd.png", ";;": ";;" }, "geometry": { "type": "Point", "coordinates": [ 4.165139, 52.403139 ] } },
{ "type": "Feature", "properties": { "Windpark": "Prinses Amaliawindpark", "Latitude": 52.594333, "Longitude": 4.212528, "Aantal_windmolens": 60, "Vermogen_per_windmolen_MW": 2.0, "Vermogen_windpark_MW": 120.0, "in_gebruik_sinds": 2008, "oppervlakte": 14, "bedrijf": "Eneco ", "foto": "https://upload.wikimedia.org/wikipedia/commons/c/cf/Prinses_Amalia_windmolenpark_4.jpg", ";;": ";;" }, "geometry": { "type": "Point", "coordinates": [ 4.212528, 52.594333 ] } },
{ "type": "Feature", "properties": { "Windpark": "Egmond aan Zee (OWEZ)", "Latitude": 52.594472, "Longitude": 4.437111, "Aantal_windmolens": 63, "Vermogen_per_windmolen_MW": 3.0, "Vermogen_windpark_MW": 108.0, "in_gebruik_sinds": 2007, "oppervlakte": 27, "bedrijf": "Shell", "foto": "https://www.informatiehuismarien.nl/publish/library/212/wind-op-zee-prinses-amalia-windpark.jpg", ";;": ";;" }, "geometry": { "type": "Point", "coordinates": [ 4.437111, 52.594472 ] } }
]
}
